dis_sdk_python/__init__.py
dis_sdk_python/com/__init__.py
dis_sdk_python/com/huaweicloud/__init__.py
dis_sdk_python/com/huaweicloud/dis/__init__.py
dis_sdk_python/com/huaweicloud/dis/sdk/__init__.py
dis_sdk_python/com/huaweicloud/dis/sdk/python/__init__.py
dis_sdk_python/com/huaweicloud/dis/sdk/python/client/__init__.py
dis_sdk_python/com/huaweicloud/dis/sdk/python/client/disclient.py
dis_sdk_python/com/huaweicloud/dis/sdk/python/models/DumpTask.py
dis_sdk_python/com/huaweicloud/dis/sdk/python/models/__init__.py
dis_sdk_python/com/huaweicloud/dis/sdk/python/models/base_model.py
dis_sdk_python/com/huaweicloud/dis/sdk/python/models/disauth.py
dis_sdk_python/com/huaweicloud/dis/sdk/python/models/disexception.py
dis_sdk_python/com/huaweicloud/dis/sdk/python/models/disrequest.py
dis_sdk_python/com/huaweicloud/dis/sdk/python/models/log.py
dis_sdk_python/com/huaweicloud/dis/sdk/python/models/model_python2.py
dis_sdk_python/com/huaweicloud/dis/sdk/python/models/model_python3.py
dis_sdk_python/com/huaweicloud/dis/sdk/python/proto/__init__.py
dis_sdk_python/com/huaweicloud/dis/sdk/python/proto/record_pb2.py
dis_sdk_python/com/huaweicloud/dis/sdk/python/response/__init__.py
dis_sdk_python/com/huaweicloud/dis/sdk/python/response/disAppresonse.py
dis_sdk_python/com/huaweicloud/dis/sdk/python/response/disConsumeresponse.py
dis_sdk_python/com/huaweicloud/dis/sdk/python/response/disGetresponse.py
dis_sdk_python/com/huaweicloud/dis/sdk/python/response/disMonitorresponse.py
dis_sdk_python/com/huaweicloud/dis/sdk/python/response/disStreamresponse.py
dis_sdk_python/com/huaweicloud/dis/sdk/python/response/disadminresponse.py
dis_sdk_python/com/huaweicloud/dis/sdk/python/response/discheckpointresponse.py
dis_sdk_python/com/huaweicloud/dis/sdk/python/response/disreadDISConfig.py
dis_sdk_python/com/huaweicloud/dis/sdk/python/response/disrecordresponse.py
dis_sdk_python/com/huaweicloud/dis/sdk/python/response/disresponse.py
dis_sdk_python/com/huaweicloud/dis/sdk/python/utils/__init__.py
huaweicloud_sdk_python_dis-2.0.7.dist-info/LICENSE
huaweicloud_sdk_python_dis-2.0.7.dist-info/METADATA
huaweicloud_sdk_python_dis-2.0.7.dist-info/WHEEL
huaweicloud_sdk_python_dis-2.0.7.dist-info/top_level.txt
huaweicloud_sdk_python_dis-2.0.7.dist-info/RECORD
